AUTHORS
LICENSE
MANIFEST.in
README
setup.py
Platypus_Router.egg-info/PKG-INFO
Platypus_Router.egg-info/SOURCES.txt
Platypus_Router.egg-info/dependency_links.txt
Platypus_Router.egg-info/requires.txt
Platypus_Router.egg-info/top_level.txt
platypus_router.egg-info/SOURCES.txt
router/__init__.py
router/core.py
router/simple_server.py
router/tests.py
router/utils.py