Metadata-Version: 1.0
Name: platypus-router
Version: 0.1.2
Summary: Django like WSGI router
Home-page: https://github.com/platypus-creation/platypus-router/
Author: Vincent Jauneau
Author-email: vincent.jauneau@platypus-creation.com
License: Copyright (c) 2011 Vincent Jauneau
